verilog/elevator_controller.v
`timescale 1ns/1ps

module elevator_top (
    input  wire       clk,
    input  wire       reset,

    input  wire [4:0] hall_up_request,
    input  wire [4:0] hall_down_request,
    input  wire [4:0] cabin_request,

    output reg  [2:0] current_floor,
    output reg  [1:0] direction,
    output reg        door_open,

    output reg  [4:0] hall_up_requests,
    output reg  [4:0] hall_down_requests,
    output reg  [4:0] cabin_requests,
    output wire [4:0] pending_requests
);

    localparam DOWN = 2'b00;
    localparam UP   = 2'b01;
    localparam IDLE = 2'b10;

    reg [2:0] door_timer;

    assign pending_requests =
        hall_up_requests |
        hall_down_requests |
        cabin_requests;


    // =========================================================
    // CHECK REQUESTS ABOVE CURRENT FLOOR
    // =========================================================
    function has_request_above;
    input [2:0] floor;
    integer i;
    begin
        has_request_above = 1'b0;

        for (i = 0; i < 5; i = i + 1) begin
            if (i > floor) begin
                if (hall_up_requests[i]   ||
                    hall_down_requests[i] ||
                    cabin_requests[i]     ||
                    hall_up_request[i]    ||
                    hall_down_request[i]  ||
                    cabin_request[i])
                    has_request_above = 1'b1;
            end
        end
    end
endfunction


    // =========================================================
    // CHECK REQUESTS BELOW CURRENT FLOOR
    // =========================================================
    function has_request_below;
        input [2:0] floor;
        integer i;
        begin
            has_request_below = 1'b0;

            for (i = 0; i < 5; i = i + 1) begin
                if (i < floor) begin
                    if (hall_up_requests[i] ||
                        hall_down_requests[i] ||
                        cabin_requests[i] ||
                        hall_up_request[i] ||
                        hall_down_request[i] ||
                        cabin_request[i])
                        has_request_below = 1'b1;
                end
            end
        end
    endfunction


    // =========================================================
    // CHECK REQUEST AT CURRENT FLOOR
    // =========================================================
    function has_request_here;
        input [2:0] floor;
        begin
            has_request_here =
                hall_up_requests[floor]   ||
                hall_down_requests[floor] ||
                cabin_requests[floor]     ||
                hall_up_request[floor]    ||
                hall_down_request[floor]  ||
                cabin_request[floor];
        end
    endfunction


    // =========================================================
    // MAIN ELEVATOR CONTROLLER
    // =========================================================
    always @(posedge clk) begin

        if (reset) begin

            current_floor <= 3'd0;
            direction <= IDLE;
            door_open <= 1'b0;
            door_timer <= 3'd0;

            hall_up_requests <= 5'b00000;
            hall_down_requests <= 5'b00000;
            cabin_requests <= 5'b00000;

        end else begin

            // =================================================
            // STORE NEW REQUESTS
            // =================================================
            hall_up_requests <=
                hall_up_requests | hall_up_request;

            hall_down_requests <=
                hall_down_requests | hall_down_request;

            cabin_requests <=
                cabin_requests | cabin_request;


            // =================================================
            // DOORS OPEN
            // =================================================
            if (door_open) begin

                if (door_timer < 3'd2) begin
                    door_timer <= door_timer + 1'b1;
                end

                else begin

                    door_open <= 1'b0;
                    door_timer <= 3'd0;

                    // -----------------------------------------
                    // CLEAR ALL REQUEST TYPES AT THIS FLOOR
                    // -----------------------------------------
                    hall_up_requests[current_floor] <= 1'b0;
                    hall_down_requests[current_floor] <= 1'b0;
                    cabin_requests[current_floor] <= 1'b0;

                end

            end


            // =================================================
            // DOORS CLOSED
            // =================================================
            else begin

                // =================================================
                // PRIORITY 1
                // CURRENT FLOOR REQUEST
                //
                // Direction DOES NOT MATTER.
                // =================================================
                if (has_request_here(current_floor)) begin

                    direction <= IDLE;
                    door_open <= 1'b1;
                    door_timer <= 3'd0;

                end


                // =================================================
                // CURRENT DIRECTION = UP
                // =================================================
                else if (direction == UP) begin

                    if (has_request_above(current_floor)) begin

                        // Continue UP
                        if (current_floor < 3'd4)
                            current_floor <= current_floor + 1'b1;

                    end

                    else if (has_request_below(current_floor)) begin

                        // No request UP.
                        // Reverse only because a real request exists DOWN.
                        direction <= DOWN;

                        if (current_floor > 3'd0)
                            current_floor <= current_floor - 1'b1;

                    end

                    else begin

                        // NOTHING ANYWHERE
                        // Stay exactly where we are.
                        direction <= IDLE;

                    end

                end


                // =================================================
                // CURRENT DIRECTION = DOWN
                // =================================================
                else if (direction == DOWN) begin

                    if (has_request_below(current_floor)) begin

                        // Continue DOWN
                        if (current_floor > 3'd0)
                            current_floor <= current_floor - 1'b1;

                    end

                    else if (has_request_above(current_floor)) begin

                        // No request DOWN.
                        // Reverse only because a real request exists UP.
                        direction <= UP;

                        if (current_floor < 3'd4)
                            current_floor <= current_floor + 1'b1;

                    end

                    else begin

                        // NOTHING ANYWHERE
                        // Stay here.
                        direction <= IDLE;

                    end

                end


                // =================================================
                // IDLE
                // =================================================
                else begin

                    // No request here because that was checked above.

                    if (has_request_above(current_floor)) begin

                        direction <= UP;
                        current_floor <= current_floor + 1'b1;

                    end

                    else if (has_request_below(current_floor)) begin

                        direction <= DOWN;
                        current_floor <= current_floor - 1'b1;

                    end

                    else begin

                        direction <= IDLE;

                    end

                end

            end

        end

    end

endmodule

verilog/elevator_tb.v
`timescale 1ns/1ps

module elevator_tb;

    reg clk;
    reg reset;

    reg [4:0] hall_up_request;
    reg [4:0] hall_down_request;
    reg [4:0] cabin_request;

    wire [2:0] current_floor;
    wire [1:0] direction;
    wire door_open;

    wire [4:0] hall_up_requests;
    wire [4:0] hall_down_requests;
    wire [4:0] cabin_requests;
    wire [4:0] pending_requests;


    // =========================================================
    // CONNECT TO ELEVATOR
    // =========================================================

    elevator_top DUT (

        .clk(clk),
        .reset(reset),

        .hall_up_request(hall_up_request),
        .hall_down_request(hall_down_request),

        .cabin_request(cabin_request),

        .current_floor(current_floor),
        .direction(direction),
        .door_open(door_open),

        .hall_up_requests(hall_up_requests),
        .hall_down_requests(hall_down_requests),

        .cabin_requests(cabin_requests),

        .pending_requests(pending_requests)

    );


    // =========================================================
    // CLOCK
    // =========================================================

    always #5 clk = ~clk;


    // =========================================================
    // DISPLAY
    // =========================================================

    always @(posedge clk) begin

        $write(
            "TIME=%0t | FLOOR=%0d | DIR=",
            $time,
            current_floor
        );

        case (direction)

            2'b00: $write("DOWN");

            2'b01: $write("UP");

            2'b10: $write("IDLE");

            default: $write("UNKNOWN");

        endcase

        $display(
            " | DOOR=%b | HALL_UP=%b | HALL_DOWN=%b | CABIN=%b | PENDING=%b",
            door_open,
            hall_up_requests,
            hall_down_requests,
            cabin_requests,
            pending_requests
        );

    end


    // =========================================================
    // CABIN REQUEST TASK
    // =========================================================

    task cabin_request_task;

        input integer floor;

        begin

            $display("");
            $display("----------------------------------------------");
            $display("CABIN REQUEST");
            $display("Passenger inside -> F%0d", floor);
            $display("----------------------------------------------");

            cabin_request = (5'b00001 << floor);

            #10;

            cabin_request = 5'b00000;

        end

    endtask


    // =========================================================
    // HALL UP REQUEST TASK
    // =========================================================

    task hall_up_task;

        input integer floor;

        begin

            $display("");
            $display("----------------------------------------------");
            $display("HALL UP REQUEST");
            $display("Person at F%0d -> UP", floor);
            $display("----------------------------------------------");

            hall_up_request = (5'b00001 << floor);

            #10;

            hall_up_request = 5'b00000;

        end

    endtask


    // =========================================================
    // HALL DOWN REQUEST TASK
    // =========================================================

    task hall_down_task;

        input integer floor;

        begin

            $display("");
            $display("----------------------------------------------");
            $display("HALL DOWN REQUEST");
            $display("Person at F%0d -> DOWN", floor);
            $display("----------------------------------------------");

            hall_down_request = (5'b00001 << floor);

            #10;

            hall_down_request = 5'b00000;

        end

    endtask


    // =========================================================
    // MAIN TEST
    // =========================================================

    initial begin

        // -----------------------------------------------------
        // VCD
        // -----------------------------------------------------

        $dumpfile("elevator.vcd");
        $dumpvars(0, elevator_tb);


        // -----------------------------------------------------
        // INITIAL VALUES
        // -----------------------------------------------------

        clk = 0;
        reset = 1;

        hall_up_request = 5'b00000;
        hall_down_request = 5'b00000;
        cabin_request = 5'b00000;


        // -----------------------------------------------------
        // RESET
        // -----------------------------------------------------

        #20;

        reset = 0;


        $display("");
        $display("=================================================");
        $display("        SMART ELEVATOR CONTROLLER TEST");
        $display("=================================================");
        $display("");
        $display("0 = G");
        $display("1 = F1");
        $display("2 = F2");
        $display("3 = F3");
        $display("4 = F4");
        $display("");


        // =====================================================
        // TEST 1
        //
        // Three passengers enter at G.
        //
        // Passenger 1 -> F4
        // Passenger 2 -> F2
        // Passenger 3 -> F3
        //
        // Outside person at F1 -> UP
        //
        // Expected:
        //
        // G -> F1 -> F2 -> F3 -> F4
        // =====================================================

        $display("");
        $display("=================================================");
        $display("TEST 1: THREE CABIN REQUESTS + F1 UP");
        $display("=================================================");


        // Passenger 1
        cabin_request_task(4);


        // Passenger 2
        cabin_request_task(2);


        // Passenger 3
        cabin_request_task(3);


        // Let elevator start moving
        #15;


        // F1 passenger presses UP
        hall_up_task(1);


        // Allow elevator to finish
        #250;


        $display("");
        $display("=================================================");
        $display("TEST 1 FINISHED");
        $display("=================================================");


        // =====================================================
        // TEST 2
        //
        // Elevator should now be at F4.
        //
        // Create:
        //
        // Passenger -> G
        //
        // Outside person at F1 -> DOWN
        //
        // Elevator should go DOWN.
        //
        // Expected:
        //
        // F4 -> F3 -> F2 -> F1
        //
        // At F1 the DOWN request is served.
        //
        // =====================================================

        $display("");
        $display("=================================================");
        $display("TEST 2: F1 DOWN REQUEST");
        $display("=================================================");


        // Passenger inside requests G
        cabin_request_task(0);


        // Allow elevator to start going DOWN
        #15;


        // Person at F1 presses DOWN
        hall_down_task(1);


        // Allow elevator to finish
        #250;


        $display("");
        $display("=================================================");
        $display("TEST 2 FINISHED");
        $display("=================================================");


        // =====================================================
        // FINAL
        // =====================================================

        $display("");
        $display("=================================================");
        $display("       SMART ELEVATOR TEST COMPLETE");
        $display("=================================================");
        $display("");

        #20;

        $finish;

    end

endmodule

verilog/elevator.vcd
$date
	Sat Sep  5 21:03:51 2026
$end
$version
	Icarus Verilog
$end
$timescale
	1ps
$end
$scope module elevator_tb $end
$var wire 5 ! pending_requests [4:0] $end
$var wire 5 " hall_up_requests [4:0] $end
$var wire 5 # hall_down_requests [4:0] $end
$var wire 1 $ door_open $end
$var wire 2 % direction [1:0] $end
$var wire 3 & current_floor [2:0] $end
$var wire 5 ' cabin_requests [4:0] $end
$var reg 5 ( cabin_request [4:0] $end
$var reg 1 ) clk $end
$var reg 5 * hall_down_request [4:0] $end
$var reg 5 + hall_up_request [4:0] $end
$var reg 1 , reset $end
$scope module DUT $end
$var wire 5 - cabin_request [4:0] $end
$var wire 1 ) clk $end
$var wire 5 . hall_down_request [4:0] $end
$var wire 5 / hall_up_request [4:0] $end
$var wire 5 0 pending_requests [4:0] $end
$var wire 1 , reset $end
$var parameter 2 1 DOWN $end
$var parameter 2 2 IDLE $end
$var parameter 2 3 UP $end
$var reg 5 4 cabin_requests [4:0] $end
$var reg 3 5 current_floor [2:0] $end
$var reg 2 6 direction [1:0] $end
$var reg 1 $ door_open $end
$var reg 3 7 door_timer [2:0] $end
$var reg 5 8 hall_down_requests [4:0] $end
$var reg 5 9 hall_up_requests [4:0] $end
$scope function has_request_above $end
$var reg 3 : floor [2:0] $end
$var integer 32 ; i [31:0] $end
$upscope $end
$scope function has_request_below $end
$var reg 3 < floor [2:0] $end
$var integer 32 = i [31:0] $end
$upscope $end
$scope function has_request_here $end
$var reg 3 > floor [2:0] $end
$upscope $end
$upscope $end
$scope task cabin_request_task $end
$var integer 32 ? floor [31:0] $end
$upscope $end
$scope task hall_down_task $end
$var integer 32 @ floor [31:0] $end
$upscope $end
$scope task hall_up_task $end
$var integer 32 A floor [31:0] $end
$upscope $end
$upscope $end
$enddefinitions $end
$comment Show the parameter values. $end
$dumpall
b1 3
b10 2
b0 1
$end
#0
$dumpvars
bx A
bx @
bx ?
bx >
bx =
bx <
bx ;
bx :
bx 9
bx 8
bx 7
bx 6
bx 5
bx 4
bx 0
b0 /
b0 .
b0 -
1,
b0 +
b0 *
0)
b0 (
bx '
bx &
bx %
x$
bx #
bx "
bx !
$end
#5000
b0 !
b0 0
b0 '
b0 4
b0 #
b0 8
b0 "
b0 9
b0 7
0$
b10 %
b10 6
b0 &
b0 5
1)
#10000
0)
#15000
1)
#20000
0)
b10000 (
b10000 -
b100 ?
0,
#25000
b10000 !
b10000 0
b1 &
b1 5
b1 %
b1 6
b10000 '
b10000 4
b101 ;
b0 :
b0 >
1)
#30000
0)
b10 ?
b100 (
b100 -
#35000
b10100 !
b10100 0
b10 &
b10 5
b10100 '
b10100 4
b101 ;
b1 :
b1 >
1)
#40000
0)
b11 ?
b1000 (
b1000 -
#45000
b11100 !
b11100 0
1$
b10 %
b10 6
b11100 '
b11100 4
b10 >
1)
#50000
0)
b0 (
b0 -
#55000
b1 7
1)
#60000
0)
#65000
b11110 !
b11110 0
b10 7
b10 "
b10 9
1)
b10 +
b10 /
b1 A
#70000
0)
#75000
b11010 !
b11010 0
b11000 '
b11000 4
b0 7
0$
1)
b0 +
b0 /
#80000
0)
#85000
b11 &
b11 5
b1 %
b1 6
b101 ;
b10 :
1)
#90000
0)
#95000
1$
b10 %
b10 6
b11 >
1)
#100000
0)
#105000
b1 7
1)
#110000
0)
#115000
b10 7
1)
#120000
0)
#125000
b10010 !
b10010 0
b10000 '
b10000 4
b0 7
0$
1)
#130000
0)
#135000
b100 &
b100 5
b1 %
b1 6
b101 ;
b11 :
1)
#140000
0)
#145000
1$
b10 %
b10 6
b100 >
1)
#150000
0)
#155000
b1 7
1)
#160000
0)
#165000
b10 7
1)
#170000
0)
#175000
b10 !
b10 0
b0 '
b0 4
b0 7
0$
1)
#180000
0)
#185000
b11 &
b11 5
b0 %
b0 6
b101 =
b100 <
b101 ;
b100 :
1)
#190000
0)
#195000
b10 &
b10 5
b101 =
b11 <
b11 >
1)
#200000
0)
#205000
b1 &
b1 5
b101 =
b10 <
b10 >
1)
#210000
0)
#215000
1$
b10 %
b10 6
b1 >
1)
#220000
0)
#225000
b1 7
1)
#230000
0)
#235000
b10 7
1)
#240000
0)
#245000
b0 !
b0 0
b0 "
b0 9
b0 7
0$
1)
#250000
0)
#255000
b101 =
b1 <
b101 ;
b1 :
1)
#260000
0)
#265000
b101 =
b101 ;
1)
#270000
0)
#275000
b101 =
b101 ;
1)
#280000
0)
#285000
b101 =
b101 ;
1)
#290000
0)
#295000
b101 =
b101 ;
1)
#300000
0)
#305000
b101 =
b101 ;
1)
#310000
0)
#315000
b101 =
b101 ;
1)
#320000
0)
#325000
b1 !
b1 0
b0 &
b0 5
b0 %
b0 6
b1 '
b1 4
b101 =
b101 ;
1)
b1 (
b1 -
b0 ?
#330000
0)
#335000
1$
b10 %
b10 6
b0 >
1)
b0 (
b0 -
#340000
0)
#345000
b1 7
1)
#350000
0)
b10 *
b10 .
b1 @
#355000
b11 !
b11 0
b10 7
b10 #
b10 8
1)
#360000
0)
b0 *
b0 .
#365000
b10 !
b10 0
b0 '
b0 4
b0 7
0$
1)
#370000
0)
#375000
b1 &
b1 5
b1 %
b1 6
b101 ;
b0 :
1)
#380000
0)
#385000
1$
b10 %
b10 6
b1 >
1)
#390000
0)
#395000
b1 7
1)
#400000
0)
#405000
b10 7
1)
#410000
0)
#415000
b0 !
b0 0
b0 #
b0 8
b0 7
0$
1)
#420000
0)
#425000
b101 =
b101 ;
b1 :
1)
#430000
0)
#435000
b101 =
b101 ;
1)
#440000
0)
#445000
b101 =
b101 ;
1)
#450000
0)
#455000
b101 =
b101 ;
1)
#460000
0)
#465000
b101 =
b101 ;
1)
#470000
0)
#475000
b101 =
b101 ;
1)
#480000
0)
#485000
b101 =
b101 ;
1)
#490000
0)
#495000
b101 =
b101 ;
1)
#500000
0)
#505000
b101 =
b101 ;
1)
#510000
0)
#515000
b101 =
b101 ;
1)
#520000
0)
#525000
b101 =
b101 ;
1)
#530000
0)
#535000
b101 =
b101 ;
1)
#540000
0)
#545000
b101 =
b101 ;
1)
#550000
0)
#555000
b101 =
b101 ;
1)
#560000
0)
#565000
b101 =
b101 ;
1)
#570000
0)
#575000
b101 =
b101 ;
1)
#580000
0)
#585000
b101 =
b101 ;
1)
#590000
0)
#595000
b101 =
b101 ;
1)
#600000
0)
#605000
b101 =
b101 ;
1)
#610000
0)
#615000
b101 =
b101 ;
1)
#620000
0)
#625000
b101 =
b101 ;
1)
