verilog/elevator_controller.v
`timescale 1ns/1ps

module elevator_top (
    input  wire       clk,
    input  wire       reset,

    input  wire [4:0] hall_up_request,
    input  wire [4:0] hall_down_request,
    input  wire [4:0] cabin_request,

    output reg  [2:0] current_floor,
    output reg  [1:0] direction,
    output reg        door_open,

    output reg  [4:0] hall_up_requests,
    output reg  [4:0] hall_down_requests,
    output reg  [4:0] cabin_requests,
    output wire [4:0] pending_requests
);

    localparam DOWN = 2'b00;
    localparam UP   = 2'b01;
    localparam IDLE = 2'b10;

    reg [2:0] door_timer;

    assign pending_requests =
        hall_up_requests |
        hall_down_requests |
        cabin_requests;


    // =========================================================
    // CHECK REQUESTS ABOVE CURRENT FLOOR
    // =========================================================
    function has_request_above;
    input [2:0] floor;
    integer i;
    begin
        has_request_above = 1'b0;

        for (i = 0; i < 5; i = i + 1) begin
            if (i > floor) begin
                if (hall_up_requests[i]   ||
                    hall_down_requests[i] ||
                    cabin_requests[i]     ||
                    hall_up_request[i]    ||
                    hall_down_request[i]  ||
                    cabin_request[i])
                    has_request_above = 1'b1;
            end
        end
    end
endfunction


    // =========================================================
    // CHECK REQUESTS BELOW CURRENT FLOOR
    // =========================================================
    function has_request_below;
        input [2:0] floor;
        integer i;
        begin
            has_request_below = 1'b0;

            for (i = 0; i < 5; i = i + 1) begin
                if (i < floor) begin
                    if (hall_up_requests[i] ||
                        hall_down_requests[i] ||
                        cabin_requests[i] ||
                        hall_up_request[i] ||
                        hall_down_request[i] ||
                        cabin_request[i])
                        has_request_below = 1'b1;
                end
            end
        end
    endfunction


    // =========================================================
    // CHECK REQUEST AT CURRENT FLOOR
    // =========================================================
    function has_request_here;
        input [2:0] floor;
        begin
            has_request_here =
                hall_up_requests[floor]   ||
                hall_down_requests[floor] ||
                cabin_requests[floor]     ||
                hall_up_request[floor]    ||
                hall_down_request[floor]  ||
                cabin_request[floor];
        end
    endfunction


    // =========================================================
    // MAIN ELEVATOR CONTROLLER
    // =========================================================
    always @(posedge clk) begin

        if (reset) begin

            current_floor <= 3'd0;
            direction <= IDLE;
            door_open <= 1'b0;
            door_timer <= 3'd0;

            hall_up_requests <= 5'b00000;
            hall_down_requests <= 5'b00000;
            cabin_requests <= 5'b00000;

        end else begin

            // =================================================
            // STORE NEW REQUESTS
            // =================================================
            hall_up_requests <=
                hall_up_requests | hall_up_request;

            hall_down_requests <=
                hall_down_requests | hall_down_request;

            cabin_requests <=
                cabin_requests | cabin_request;


            // =================================================
            // DOORS OPEN
            // =================================================
            if (door_open) begin

                if (door_timer < 3'd2) begin
                    door_timer <= door_timer + 1'b1;
                end

                else begin

                    door_open <= 1'b0;
                    door_timer <= 3'd0;

                    // -----------------------------------------
                    // CLEAR ALL REQUEST TYPES AT THIS FLOOR
                    // -----------------------------------------
                    hall_up_requests[current_floor] <= 1'b0;
                    hall_down_requests[current_floor] <= 1'b0;
                    cabin_requests[current_floor] <= 1'b0;

                end

            end


            // =================================================
            // DOORS CLOSED
            // =================================================
            else begin

                // =================================================
                // PRIORITY 1
                // CURRENT FLOOR REQUEST
                //
                // Direction DOES NOT MATTER.
                // =================================================
                if (has_request_here(current_floor)) begin

                    direction <= IDLE;
                    door_open <= 1'b1;
                    door_timer <= 3'd0;

                end


                // =================================================
                // CURRENT DIRECTION = UP
                // =================================================
                else if (direction == UP) begin

                    if (has_request_above(current_floor)) begin

                        // Continue UP
                        if (current_floor < 3'd4)
                            current_floor <= current_floor + 1'b1;

                    end

                    else if (has_request_below(current_floor)) begin

                        // No request UP.
                        // Reverse only because a real request exists DOWN.
                        direction <= DOWN;

                        if (current_floor > 3'd0)
                            current_floor <= current_floor - 1'b1;

                    end

                    else begin

                        // NOTHING ANYWHERE
                        // Stay exactly where we are.
                        direction <= IDLE;

                    end

                end


                // =================================================
                // CURRENT DIRECTION = DOWN
                // =================================================
                else if (direction == DOWN) begin

                    if (has_request_below(current_floor)) begin

                        // Continue DOWN
                        if (current_floor > 3'd0)
                            current_floor <= current_floor - 1'b1;

                    end

                    else if (has_request_above(current_floor)) begin

                        // No request DOWN.
                        // Reverse only because a real request exists UP.
                        direction <= UP;

                        if (current_floor < 3'd4)
                            current_floor <= current_floor + 1'b1;

                    end

                    else begin

                        // NOTHING ANYWHERE
                        // Stay here.
                        direction <= IDLE;

                    end

                end


                // =================================================
                // IDLE
                // =================================================
                else begin

                    // No request here because that was checked above.

                    if (has_request_above(current_floor)) begin

                        direction <= UP;
                        current_floor <= current_floor + 1'b1;

                    end

                    else if (has_request_below(current_floor)) begin

                        direction <= DOWN;
                        current_floor <= current_floor - 1'b1;

                    end

                    else begin

                        direction <= IDLE;

                    end

                end

            end

        end

    end

endmodule

verilog/elevator_random_tb.v
`timescale 1ns/1ps

module elevator_random_tb;

    reg clk;
    reg reset;

    reg [4:0] hall_up_request;
    reg [4:0] hall_down_request;
    reg [4:0] cabin_request;

    wire [2:0] current_floor;
    wire [1:0] direction;
    wire door_open;

    wire [4:0] hall_up_requests;
    wire [4:0] hall_down_requests;
    wire [4:0] cabin_requests;
    wire [4:0] pending_requests;


    // =========================================================
    // DUT
    // =========================================================

    elevator_top DUT (

        .clk(clk),
        .reset(reset),

        .hall_up_request(hall_up_request),
        .hall_down_request(hall_down_request),

        .cabin_request(cabin_request),

        .current_floor(current_floor),
        .direction(direction),
        .door_open(door_open),

        .hall_up_requests(hall_up_requests),
        .hall_down_requests(hall_down_requests),

        .cabin_requests(cabin_requests),
        .pending_requests(pending_requests)

    );


    // =========================================================
    // CLOCK
    // =========================================================

    always #5 clk = ~clk;


    // =========================================================
    // STATUS
    // =========================================================

    always @(posedge clk) begin

        $write(
            "TIME=%0t | FLOOR=%0d | DIR=",
            $time,
            current_floor
        );

        case(direction)

            2'b00: $write("DOWN");
            2'b01: $write(" UP");
            2'b10: $write("IDLE");
            default: $write("UNKNOWN");

        endcase

        $display(
            " | DOOR=%b | UP=%b | DOWN=%b | CABIN=%b | PENDING=%b",
            door_open,
            hall_up_requests,
            hall_down_requests,
            cabin_requests,
            pending_requests
        );

    end


    // =========================================================
    // CABIN REQUEST
    // =========================================================

    task cabin_request_task;

        input integer floor;

        begin

            $display("");
            $display("----------------------------------------------");
            $display("RANDOM CABIN REQUEST");
            $display("Passenger -> F%0d", floor);
            $display("----------------------------------------------");

            cabin_request = (5'b00001 << floor);

            #10;

            cabin_request = 5'b00000;

        end

    endtask


    // =========================================================
    // HALL UP REQUEST
    // =========================================================

    task hall_up_task;

        input integer floor;

        begin

            $display("");
            $display("----------------------------------------------");
            $display("RANDOM HALL UP REQUEST");
            $display("Person at F%0d -> UP", floor);
            $display("----------------------------------------------");

            hall_up_request = (5'b00001 << floor);

            #10;

            hall_up_request = 5'b00000;

        end

    endtask


    // =========================================================
    // HALL DOWN REQUEST
    // =========================================================

    task hall_down_task;

        input integer floor;

        begin

            $display("");
            $display("----------------------------------------------");
            $display("RANDOM HALL DOWN REQUEST");
            $display("Person at F%0d -> DOWN", floor);
            $display("----------------------------------------------");

            hall_down_request = (5'b00001 << floor);

            #10;

            hall_down_request = 5'b00000;

        end

    endtask


    // =========================================================
    // MAIN TEST
    // =========================================================

    initial begin

        $dumpfile("elevator_random.vcd");
        $dumpvars(0, elevator_random_tb);


        clk = 0;
        reset = 1;

        hall_up_request   = 5'b00000;
        hall_down_request = 5'b00000;
        cabin_request     = 5'b00000;


        // =====================================================
        // RESET
        // =====================================================

        #20;

        reset = 0;


        $display("");
        $display("=================================================");
        $display("       RANDOM REQUEST STRESS TEST");
        $display("=================================================");
        $display("");


        // =====================================================
        // TEST 1
        // Multiple requests almost simultaneously
        // =====================================================

        $display("TEST 1: MULTIPLE RANDOM REQUESTS");


        cabin_request_task(4);

        #7;

        cabin_request_task(2);

        #13;

        hall_up_task(1);

        #8;

        cabin_request_task(3);

        #11;

        hall_down_task(4);


        // =====================================================
        // Let elevator process
        // =====================================================

        #150;


        // =====================================================
        // TEST 2
        // Requests while elevator is moving
        // =====================================================

        $display("");
        $display("=================================================");
        $display("TEST 2: REQUESTS WHILE MOVING");
        $display("=================================================");


        cabin_request_task(4);

        #17;

        hall_up_task(2);

        #9;

        hall_down_task(3);

        #12;

        cabin_request_task(1);

        #14;

        hall_down_task(0);


        // =====================================================
        // Let elevator process
        // =====================================================

        #250;


        // =====================================================
        // TEST 3
        // Heavy random traffic
        // =====================================================

        $display("");
        $display("=================================================");
        $display("TEST 3: HEAVY RANDOM TRAFFIC");
        $display("=================================================");


        cabin_request_task(3);

        #6;

        hall_up_task(1);

        #9;

        cabin_request_task(4);

        #5;

        hall_down_task(3);

        #11;

        cabin_request_task(2);

        #7;

        hall_up_task(0);

        #8;

        hall_down_task(4);

        #6;

        cabin_request_task(1);

        #10;

        hall_up_task(2);


        // =====================================================
        // Allow everything to finish
        // =====================================================

        #800;


        $display("");
        $display("=================================================");
        $display("       RANDOM STRESS TEST COMPLETE");
        $display("=================================================");


        #20;

        $finish;

    end

endmodule

verilog/elevator_random.vcd
$date
	Tue Sep  1 23:25:55 2026
$end
$version
	Icarus Verilog
$end
$timescale
	1ps
$end
$scope module elevator_random_tb $end
$var wire 5 ! pending_requests [4:0] $end
$var wire 5 " hall_up_requests [4:0] $end
$var wire 5 # hall_down_requests [4:0] $end
$var wire 1 $ door_open $end
$var wire 2 % direction [1:0] $end
$var wire 3 & current_floor [2:0] $end
$var wire 5 ' cabin_requests [4:0] $end
$var reg 5 ( cabin_request [4:0] $end
$var reg 1 ) clk $end
$var reg 5 * hall_down_request [4:0] $end
$var reg 5 + hall_up_request [4:0] $end
$var reg 1 , reset $end
$scope module DUT $end
$var wire 5 - cabin_request [4:0] $end
$var wire 1 ) clk $end
$var wire 5 . hall_down_request [4:0] $end
$var wire 5 / hall_up_request [4:0] $end
$var wire 5 0 pending_requests [4:0] $end
$var wire 1 , reset $end
$var parameter 2 1 DOWN $end
$var parameter 2 2 IDLE $end
$var parameter 2 3 UP $end
$var reg 5 4 cabin_requests [4:0] $end
$var reg 3 5 current_floor [2:0] $end
$var reg 2 6 direction [1:0] $end
$var reg 1 $ door_open $end
$var reg 3 7 door_timer [2:0] $end
$var reg 5 8 hall_down_requests [4:0] $end
$var reg 5 9 hall_up_requests [4:0] $end
$scope function has_request_above $end
$var reg 3 : floor [2:0] $end
$var integer 32 ; i [31:0] $end
$upscope $end
$scope function has_request_below $end
$var reg 3 < floor [2:0] $end
$var integer 32 = i [31:0] $end
$upscope $end
$scope function has_request_here $end
$var reg 3 > floor [2:0] $end
$upscope $end
$upscope $end
$scope task cabin_request_task $end
$var integer 32 ? floor [31:0] $end
$upscope $end
$scope task hall_down_task $end
$var integer 32 @ floor [31:0] $end
$upscope $end
$scope task hall_up_task $end
$var integer 32 A floor [31:0] $end
$upscope $end
$upscope $end
$enddefinitions $end
$comment Show the parameter values. $end
$dumpall
b1 3
b10 2
b0 1
$end
#0
$dumpvars
bx A
bx @
bx ?
bx >
bx =
bx <
bx ;
bx :
bx 9
bx 8
bx 7
bx 6
bx 5
bx 4
bx 0
b0 /
b0 .
b0 -
1,
b0 +
b0 *
0)
b0 (
bx '
bx &
bx %
x$
bx #
bx "
bx !
$end
#5000
b0 !
b0 0
b0 '
b0 4
b0 #
b0 8
b0 "
b0 9
b0 7
0$
b10 %
b10 6
b0 &
b0 5
1)
#10000
0)
#15000
1)
#20000
0)
b10000 (
b10000 -
b100 ?
0,
#25000
b10000 !
b10000 0
b10000 '
b10000 4
b101 =
b0 <
b101 ;
b0 :
b0 >
1)
#30000
0)
b0 (
b0 -
#35000
b1 &
b1 5
b1 %
b1 6
b101 ;
1)
#37000
b100 (
b100 -
b10 ?
#40000
0)
#45000
b10100 !
b10100 0
b10 &
b10 5
b10100 '
b10100 4
b101 ;
b1 :
b1 >
1)
#47000
b0 (
b0 -
#50000
0)
#55000
1$
b10 %
b10 6
b10 >
1)
#60000
0)
b10 +
b10 /
b1 A
#65000
b10110 !
b10110 0
b1 7
b10 "
b10 9
1)
#70000
0)
b0 +
b0 /
#75000
b10 7
1)
#78000
b1000 (
b1000 -
b11 ?
#80000
0)
#85000
b11010 !
b11010 0
b0 7
0$
b11000 '
b11000 4
1)
#88000
b0 (
b0 -
#90000
0)
#95000
b11 &
b11 5
b1 %
b1 6
b101 ;
b10 :
1)
#99000
b10000 *
b10000 .
b100 @
#100000
0)
#105000
1$
b10 %
b10 6
b10000 #
b10000 8
b11 >
1)
#109000
b0 *
b0 .
#110000
0)
#115000
b1 7
1)
#120000
0)
#125000
b10 7
1)
#130000
0)
#135000
b10010 !
b10010 0
b10000 '
b10000 4
b0 7
0$
1)
#140000
0)
#145000
b100 &
b100 5
b1 %
b1 6
b101 ;
b11 :
1)
#150000
0)
#155000
1$
b10 %
b10 6
b100 >
1)
#160000
0)
#165000
b1 7
1)
#170000
0)
#175000
b10 7
1)
#180000
0)
#185000
b10 !
b10 0
b0 '
b0 4
b0 #
b0 8
b0 7
0$
1)
#190000
0)
#195000
b11 &
b11 5
b0 %
b0 6
b101 =
b100 <
b101 ;
b100 :
1)
#200000
0)
#205000
b10 &
b10 5
b101 =
b11 <
b11 >
1)
#210000
0)
#215000
b1 &
b1 5
b101 =
b10 <
b10 >
1)
#220000
0)
#225000
1$
b10 %
b10 6
b1 >
1)
#230000
0)
#235000
b1 7
1)
#240000
0)
#245000
b10 7
1)
#250000
0)
#255000
b0 !
b0 0
b0 "
b0 9
b0 7
0$
1)
#259000
b10000 (
b10000 -
b100 ?
#260000
0)
#265000
b10000 !
b10000 0
b10000 '
b10000 4
b101 =
b1 <
b101 ;
b1 :
1)
#269000
b0 (
b0 -
#270000
0)
#275000
b10 &
b10 5
b1 %
b1 6
b101 ;
1)
#280000
0)
#285000
b11 &
b11 5
b101 ;
b10 :
b10 >
1)
#286000
b100 +
b100 /
b10 A
#290000
0)
#295000
b10100 !
b10100 0
b100 &
b100 5
b100 "
b100 9
b101 ;
b11 :
b11 >
1)
#296000
b0 +
b0 /
#300000
0)
#305000
b11100 !
b11100 0
1$
b10 %
b10 6
b1000 #
b1000 8
b100 >
1)
b1000 *
b1000 .
b11 @
#310000
0)
#315000
b1 7
1)
b0 *
b0 .
#320000
0)
#325000
b10 7
1)
#327000
b10 (
b10 -
b1 ?
#330000
0)
#335000
b1110 !
b1110 0
b0 7
0$
b10 '
b10 4
1)
#337000
b0 (
b0 -
#340000
0)
#345000
b11 &
b11 5
b0 %
b0 6
b101 =
b100 <
b101 ;
b100 :
1)
#350000
0)
#351000
b1 *
b1 .
b0 @
#355000
b1111 !
b1111 0
1$
b10 %
b10 6
b1001 #
b1001 8
b11 >
1)
#360000
0)
#361000
b0 *
b0 .
#365000
b1 7
1)
#370000
0)
#375000
b10 7
1)
#380000
0)
#385000
b111 !
b111 0
b1 #
b1 8
b0 7
0$
1)
#390000
0)
#395000
b10 &
b10 5
b0 %
b0 6
b101 =
b11 <
b101 ;
b11 :
1)
#400000
0)
#405000
1$
b10 %
b10 6
b10 >
1)
#410000
0)
#415000
b1 7
1)
#420000
0)
#425000
b10 7
1)
#430000
0)
#435000
b11 !
b11 0
b0 "
b0 9
b0 7
0$
1)
#440000
0)
#445000
b1 &
b1 5
b0 %
b0 6
b101 =
b10 <
b101 ;
b10 :
1)
#450000
0)
#455000
1$
b10 %
b10 6
b1 >
1)
#460000
0)
#465000
b1 7
1)
#470000
0)
#475000
b10 7
1)
#480000
0)
#485000
b1 !
b1 0
b0 '
b0 4
b0 7
0$
1)
#490000
0)
#495000
b0 &
b0 5
b0 %
b0 6
b101 =
b1 <
b101 ;
b1 :
1)
#500000
0)
#505000
1$
b10 %
b10 6
b0 >
1)
#510000
0)
#515000
b1 7
1)
#520000
0)
#525000
b10 7
1)
#530000
0)
#535000
b0 !
b0 0
b0 #
b0 8
b0 7
0$
1)
#540000
0)
#545000
b101 =
b0 <
b101 ;
b0 :
1)
#550000
0)
#555000
b101 =
b101 ;
1)
#560000
0)
#565000
b101 =
b101 ;
1)
#570000
0)
#575000
b101 =
b101 ;
1)
#580000
0)
#585000
b101 =
b101 ;
1)
#590000
0)
#595000
b101 =
b101 ;
1)
#600000
0)
#605000
b101 =
b101 ;
1)
#610000
0)
#611000
b1000 (
b1000 -
b11 ?
#615000
b1000 !
b1000 0
b1000 '
b1000 4
b101 =
b101 ;
1)
#620000
0)
#621000
b0 (
b0 -
#625000
b1 &
b1 5
b1 %
b1 6
b101 ;
1)
#627000
b10 +
b10 /
b1 A
#630000
0)
#635000
b1010 !
b1010 0
b10 &
b10 5
b10 "
b10 9
b101 ;
b1 :
b1 >
1)
#637000
b0 +
b0 /
#640000
0)
#645000
b11 &
b11 5
b101 ;
b10 :
b10 >
1)
#646000
b10000 (
b10000 -
b100 ?
#650000
0)
#655000
b11010 !
b11010 0
1$
b10 %
b10 6
b11000 '
b11000 4
b11 >
1)
#656000
b0 (
b0 -
#660000
0)
#661000
b1000 *
b1000 .
b11 @
#665000
b1 7
b1000 #
b1000 8
1)
#670000
0)
#671000
b0 *
b0 .
#675000
b10 7
1)
#680000
0)
#682000
b100 (
b100 -
b10 ?
#685000
b10110 !
b10110 0
b0 #
b0 8
b0 7
0$
b10100 '
b10100 4
1)
#690000
0)
#692000
b0 (
b0 -
#695000
b100 &
b100 5
b1 %
b1 6
b101 ;
b11 :
1)
#699000
b1 +
b1 /
b0 A
#700000
0)
#705000
b10111 !
b10111 0
1$
b10 %
b10 6
b11 "
b11 9
b100 >
1)
#709000
b0 +
b0 /
#710000
0)
#715000
b1 7
1)
#717000
b10000 *
b10000 .
b100 @
#720000
0)
#725000
b10 7
b10000 #
b10000 8
1)
#727000
b0 *
b0 .
#730000
0)
#733000
b10 (
b10 -
b1 ?
#735000
b111 !
b111 0
b0 #
b0 8
b0 7
0$
b110 '
b110 4
1)
#740000
0)
#743000
b0 (
b0 -
#745000
b11 &
b11 5
b0 %
b0 6
b101 =
b100 <
b101 ;
b100 :
1)
#750000
0)
#753000
b100 +
b100 /
b10 A
#755000
b10 &
b10 5
b111 "
b111 9
b101 =
b11 <
b11 >
1)
#760000
0)
#763000
b0 +
b0 /
#765000
1$
b10 %
b10 6
b10 >
1)
#770000
0)
#775000
b1 7
1)
#780000
0)
#785000
b10 7
1)
#790000
0)
#795000
b11 !
b11 0
b10 '
b10 4
b11 "
b11 9
b0 7
0$
1)
#800000
0)
#805000
b1 &
b1 5
b0 %
b0 6
b101 =
b10 <
b101 ;
b10 :
1)
#810000
0)
#815000
1$
b10 %
b10 6
b1 >
1)
#820000
0)
#825000
b1 7
1)
#830000
0)
#835000
b10 7
1)
#840000
0)
#845000
b1 !
b1 0
b0 '
b0 4
b1 "
b1 9
b0 7
0$
1)
#850000
0)
#855000
b0 &
b0 5
b0 %
b0 6
b101 =
b1 <
b101 ;
b1 :
1)
#860000
0)
#865000
1$
b10 %
b10 6
b0 >
1)
#870000
0)
#875000
b1 7
1)
#880000
0)
#885000
b10 7
1)
#890000
0)
#895000
b0 !
b0 0
b0 "
b0 9
b0 7
0$
1)
#900000
0)
#905000
b101 =
b0 <
b101 ;
b0 :
1)
#910000
0)
#915000
b101 =
b101 ;
1)
#920000
0)
#925000
b101 =
b101 ;
1)
#930000
0)
#935000
b101 =
b101 ;
1)
#940000
0)
#945000
b101 =
b101 ;
1)
#950000
0)
#955000
b101 =
b101 ;
1)
#960000
0)
#965000
b101 =
b101 ;
1)
#970000
0)
#975000
b101 =
b101 ;
1)
#980000
0)
#985000
b101 =
b101 ;
1)
#990000
0)
#995000
b101 =
b101 ;
1)
#1000000
0)
#1005000
b101 =
b101 ;
1)
#1010000
0)
#1015000
b101 =
b101 ;
1)
#1020000
0)
#1025000
b101 =
b101 ;
1)
#1030000
0)
#1035000
b101 =
b101 ;
1)
#1040000
0)
#1045000
b101 =
b101 ;
1)
#1050000
0)
#1055000
b101 =
b101 ;
1)
#1060000
0)
#1065000
b101 =
b101 ;
1)
#1070000
0)
#1075000
b101 =
b101 ;
1)
#1080000
0)
#1085000
b101 =
b101 ;
1)
#1090000
0)
#1095000
b101 =
b101 ;
1)
#1100000
0)
#1105000
b101 =
b101 ;
1)
#1110000
0)
#1115000
b101 =
b101 ;
1)
#1120000
0)
#1125000
b101 =
b101 ;
1)
#1130000
0)
#1135000
b101 =
b101 ;
1)
#1140000
0)
#1145000
b101 =
b101 ;
1)
#1150000
0)
#1155000
b101 =
b101 ;
1)
#1160000
0)
#1165000
b101 =
b101 ;
1)
#1170000
0)
#1175000
b101 =
b101 ;
1)
#1180000
0)
#1185000
b101 =
b101 ;
1)
#1190000
0)
#1195000
b101 =
b101 ;
1)
#1200000
0)
#1205000
b101 =
b101 ;
1)
#1210000
0)
#1215000
b101 =
b101 ;
1)
#1220000
0)
#1225000
b101 =
b101 ;
1)
#1230000
0)
#1235000
b101 =
b101 ;
1)
#1240000
0)
#1245000
b101 =
b101 ;
1)
#1250000
0)
#1255000
b101 =
b101 ;
1)
#1260000
0)
#1265000
b101 =
b101 ;
1)
#1270000
0)
#1275000
b101 =
b101 ;
1)
#1280000
0)
#1285000
b101 =
b101 ;
1)
#1290000
0)
#1295000
b101 =
b101 ;
1)
#1300000
0)
#1305000
b101 =
b101 ;
1)
#1310000
0)
#1315000
b101 =
b101 ;
1)
#1320000
0)
#1325000
b101 =
b101 ;
1)
#1330000
0)
#1335000
b101 =
b101 ;
1)
#1340000
0)
#1345000
b101 =
b101 ;
1)
#1350000
0)
#1355000
b101 =
b101 ;
1)
#1360000
0)
#1365000
b101 =
b101 ;
1)
#1370000
0)
#1375000
b101 =
b101 ;
1)
#1380000
0)
#1385000
b101 =
b101 ;
1)
#1390000
0)
#1395000
b101 =
b101 ;
1)
#1400000
0)
#1405000
b101 =
b101 ;
1)
#1410000
0)
#1415000
b101 =
b101 ;
1)
#1420000
0)
#1425000
b101 =
b101 ;
1)
#1430000
0)
#1435000
b101 =
b101 ;
1)
#1440000
0)
#1445000
b101 =
b101 ;
1)
#1450000
0)
#1455000
b101 =
b101 ;
1)
#1460000
0)
#1465000
b101 =
b101 ;
1)
#1470000
0)
#1475000
b101 =
b101 ;
1)
#1480000
0)
#1485000
b101 =
b101 ;
1)
#1490000
0)
#1495000
b101 =
b101 ;
1)
#1500000
0)
#1505000
b101 =
b101 ;
1)
#1510000
0)
#1515000
b101 =
b101 ;
1)
#1520000
0)
#1525000
b101 =
b101 ;
1)
#1530000
0)
#1535000
b101 =
b101 ;
1)
#1540000
0)
#1545000
b101 =
b101 ;
1)
#1550000
0)
#1555000
b101 =
b101 ;
1)
#1560000
0)
#1565000
b101 =
b101 ;
1)
#1570000
0)
#1575000
b101 =
b101 ;
1)
